{
  "annotations": {
    "list": [
      {
        "builtIn": 1,
        "datasource": "-- Grafana --",
        "enable": true,
        "hide": true,
        "iconColor": "rgba(0, 211, 255, 1)",
        "name": "Annotations & Alerts",
        "target": {
          "limit": 100,
          "matchAny": false,
          "tags": [],
          "type": "dashboard"
        },
        "type": "dashboard"
      }
    ]
  },
  "editable": true,
  "fiscalYearStartMonth": 0,
  "gnetId": null,
  "graphTooltip": 2,
  "id": 5,
  "iteration": 1638371097875,
  "links": [
    {
      "asDropdown": false,
      "icon": "external link",
      "includeVars": false,
      "keepTime": true,
      "tags": [
        "couchbase-inventory"
      ],
      "targetBlank": false,
      "title": "Couchbase Inventory",
      "tooltip": "",
      "type": "dashboards",
      "url": ""
    }
  ],
  "liveNow": false,
  "panels": [
    {
      "datasource": null,
      "gridPos": {
        "h": 1,
        "w": 24,
        "x": 0,
        "y": 0
      },
      "id": 52,
      "title": "Overview - at a glance",
      "type": "row"
    },
    {
      "datasource": "JSON API",
      "fieldConfig": {
        "defaults": {
          "color": {
            "mode": "fixed"
          },
          "mappings": [],
          "thresholds": {
            "mode": "absolute",
            "steps": [
              {
                "color": "text",
                "value": null
              }
            ]
          }
        },
        "overrides": []
      },
      "gridPos": {
        "h": 3,
        "w": 5,
        "x": 0,
        "y": 1
      },
      "id": 70,
      "interval": null,
      "options": {
        "colorMode": "value",
        "graphMode": "none",
        "justifyMode": "auto",
        "orientation": "auto",
        "reduceOptions": {
          "calcs": [
            "lastNotNull"
          ],
          "fields": "",
          "values": false
        },
        "text": {},
        "textMode": "auto"
      },
      "pluginVersion": "8.2.5",
      "targets": [
        {
          "cacheDurationSeconds": 300,
          "fields": [
            {
              "jsonPath": "$cluster",
              "language": "jsonata",
              "name": "Cluster Name",
              "type": "number"
            }
          ],
          "method": "GET",
          "queryParams": "",
          "refId": "A",
          "urlPath": "/clusters/$cluster_uuid"
        }
      ],
      "timeFrom": null,
      "timeShift": null,
      "title": "Cluster Name",
      "transformations": [],
      "type": "stat"
    },
    {
      "datasource": null,
      "description": "Scroll down to \"basic info\" to see the exact alerts.",
      "fieldConfig": {
        "defaults": {
          "color": {
            "mode": "thresholds"
          },
          "mappings": [],
          "noValue": "0",
          "thresholds": {
            "mode": "absolute",
            "steps": [
              {
                "color": "#55a64bb0",
                "value": null
              },
              {
                "color": "#e02f44b0",
                "value": 1
              }
            ]
          }
        },
        "overrides": []
      },
      "gridPos": {
        "h": 8,
        "w": 4,
        "x": 5,
        "y": 1
      },
      "id": 66,
      "options": {
        "colorMode": "background",
        "graphMode": "none",
        "justifyMode": "center",
        "orientation": "auto",
        "reduceOptions": {
          "calcs": [
            "lastNotNull"
          ],
          "fields": "",
          "values": false
        },
        "text": {},
        "textMode": "value"
      },
      "pluginVersion": "8.2.5",
      "targets": [
        {
          "exemplar": true,
          "expr": "count(multimanager_cluster_checker_status{cluster_uuid=\"$cluster_uuid\"} >= 30)",
          "instant": true,
          "interval": "",
          "legendFormat": "Cluster",
          "refId": "A"
        }
      ],
      "title": "Critical Alerts",
      "transformations": [],
      "type": "stat"
    },
    {
      "datasource": "JSON API",
      "description": "Click on each service to be taken to its dashboard page.",
      "fieldConfig": {
        "defaults": {
          "color": {
            "mode": "thresholds"
          },
          "mappings": [],
          "thresholds": {
            "mode": "absolute",
            "steps": [
              {
                "color": "#bcbcbc3d",
                "value": null
              },
              {
                "color": "#55a64b",
                "value": 1
              }
            ]
          }
        },
        "overrides": [
          {
            "matcher": {
              "id": "byName",
              "options": "Data"
            },
            "properties": [
              {
                "id": "links",
                "value": [
                  {
                    "title": "Data",
                    "url": "/d/4vnZHfcnk/data-service-overview?orgId=1&${cluster:queryparam}&${cluster_uuid:queryparam}"
                  }
                ]
              }
            ]
          },
          {
            "matcher": {
              "id": "byName",
              "options": "Index"
            },
            "properties": [
              {
                "id": "links",
                "value": [
                  {
                    "title": "Index",
                    "url": "/d/zlHletp7k/index-service-overview?orgId=1&${cluster:queryparam}&${cluster_uuid:queryparam}"
                  }
                ]
              }
            ]
          },
          {
            "matcher": {
              "id": "byName",
              "options": "Search"
            },
            "properties": [
              {
                "id": "links",
                "value": [
                  {
                    "title": "Search",
                    "url": "/d/5O4ki2tnz/search-service-overview?orgId=1&${cluster:queryparam}&${cluster_uuid:queryparam}"
                  }
                ]
              }
            ]
          },
          {
            "matcher": {
              "id": "byName",
              "options": "Query"
            },
            "properties": [
              {
                "id": "links",
                "value": [
                  {
                    "title": "Query",
                    "url": "/d/89ydpf5nz/query-service-overview?orgId=1&${cluster:queryparam}&${cluster_uuid:queryparam}"
                  }
                ]
              }
            ]
          }
        ]
      },
      "gridPos": {
        "h": 8,
        "w": 15,
        "x": 9,
        "y": 1
      },
      "id": 97,
      "options": {
        "colorMode": "background",
        "graphMode": "none",
        "justifyMode": "auto",
        "orientation": "auto",
        "reduceOptions": {
          "calcs": [
            "max"
          ],
          "fields": "/.*/",
          "values": false
        },
        "text": {},
        "textMode": "name"
      },
      "pluginVersion": "8.2.5",
      "targets": [
        {
          "cacheDurationSeconds": 0,
          "fields": [
            {
              "jsonPath": "$.nodes_summary.services ~> $filter(function($svc) {$svc = \"kv\"}) ~> $count",
              "language": "jsonata",
              "name": "Data"
            },
            {
              "jsonPath": "$.nodes_summary.services ~> $filter(function($svc) {$svc = \"index\"}) ~> $count",
              "language": "jsonata",
              "name": "Index"
            },
            {
              "jsonPath": "$.nodes_summary.services ~> $filter(function($svc) {$svc = \"fts\"}) ~> $count",
              "language": "jsonata",
              "name": "Search"
            },
            {
              "jsonPath": "$.nodes_summary.services ~> $filter(function($svc) {$svc = \"n1ql\"}) ~> $count",
              "language": "jsonata",
              "name": "Query"
            },
            {
              "jsonPath": "$.nodes_summary.services ~> $filter(function($svc) {$svc = \"eventing\"}) ~> $count",
              "language": "jsonata",
              "name": "Eventing"
            },
            {
              "jsonPath": "$.nodes_summary.services ~> $filter(function($svc) {$svc = \"cbas\"}) ~> $count",
              "language": "jsonata",
              "name": "Analytics"
            },
            {
              "jsonPath": "$.nodes_summary.services ~> $filter(function($svc) {$svc = \"backup\"}) ~> $count",
              "language": "jsonata",
              "name": "Backup"
            },
            {
              "jsonPath": "0",
              "language": "jsonata",
              "name": "..."
            }
          ],
          "method": "GET",
          "queryParams": "",
          "refId": "A",
          "urlPath": "/clusters"
        }
      ],
      "title": "Running Services (clickable!)",
      "transformations": [
        {
          "id": "seriesToRows",
          "options": {}
        }
      ],
      "type": "stat"
    },
    {
      "datasource": "JSON API",
      "fieldConfig": {
        "defaults": {
          "color": {
            "mode": "fixed"
          },
          "mappings": [],
          "thresholds": {
            "mode": "absolute",
            "steps": [
              {
                "color": "text",
                "value": null
              }
            ]
          }
        },
        "overrides": []
      },
      "gridPos": {
        "h": 5,
        "w": 5,
        "x": 0,
        "y": 4
      },
      "id": 54,
      "interval": null,
      "options": {
        "colorMode": "value",
        "graphMode": "none",
        "justifyMode": "auto",
        "orientation": "auto",
        "reduceOptions": {
          "calcs": [
            "lastNotNull"
          ],
          "fields": "/^Version$/",
          "values": false
        },
        "text": {},
        "textMode": "auto"
      },
      "pluginVersion": "8.2.5",
      "targets": [
        {
          "cacheDurationSeconds": 300,
          "fields": [
            {
              "jsonPath": "$map($.nodes_summary[*].version, function($m) {$join($append($split($m, \"-\")[0], $replace($split($m, \"-\")[2], \"e\", \"E\", 1)), \" \")})",
              "language": "jsonata",
              "name": "Version",
              "type": "number"
            }
          ],
          "method": "GET",
          "queryParams": "",
          "refId": "A",
          "urlPath": "/clusters/$cluster_uuid"
        }
      ],
      "timeFrom": null,
      "timeShift": null,
      "title": "Version",
      "transformations": [],
      "type": "stat"
    },
    {
      "datasource": "JSON API",
      "description": "",
      "fieldConfig": {
        "defaults": {
          "color": {
            "mode": "fixed"
          },
          "mappings": [],
          "thresholds": {
            "mode": "absolute",
            "steps": [
              {
                "color": "text",
                "value": null
              }
            ]
          }
        },
        "overrides": []
      },
      "gridPos": {
        "h": 5,
        "w": 3,
        "x": 0,
        "y": 9
      },
      "id": 56,
      "options": {
        "colorMode": "value",
        "graphMode": "area",
        "justifyMode": "auto",
        "orientation": "auto",
        "reduceOptions": {
          "calcs": [
            "lastNotNull"
          ],
          "fields": "",
          "values": true
        },
        "text": {},
        "textMode": "value"
      },
      "pluginVersion": "8.2.5",
      "targets": [
        {
          "cacheDurationSeconds": 0,
          "fields": [
            {
              "jsonPath": "$count($.nodes_summary[*])",
              "language": "jsonata",
              "name": "Number of nodes"
            }
          ],
          "method": "GET",
          "queryParams": "",
          "refId": "A",
          "urlPath": "/clusters/$cluster_uuid"
        }
      ],
      "title": "Nodes",
      "type": "stat"
    },
    {
      "datasource": "-- Mixed --",
      "description": "Couchbase recommends a minimum of 8 CPUs, 8GB RAM, and keeping RAM usage below 80%.",
      "fieldConfig": {
        "defaults": {
          "color": {
            "mode": "thresholds"
          },
          "custom": {
            "align": "center",
            "displayMode": "auto",
            "minWidth": 1
          },
          "mappings": [],
          "thresholds": {
            "mode": "absolute",
            "steps": [
              {
                "color": "text",
                "value": null
              }
            ]
          }
        },
        "overrides": [
          {
            "matcher": {
              "id": "byName",
              "options": "CPUs"
            },
            "properties": [
              {
                "id": "custom.width",
                "value": 60
              },
              {
                "id": "custom.displayMode",
                "value": "color-background-solid"
              },
              {
                "id": "thresholds",
                "value": {
                  "mode": "absolute",
                  "steps": [
                    {
                      "color": "#e02f44b0",
                      "value": null
                    },
                    {
                      "color": "#55a64bb0",
                      "value": 8
                    }
                  ]
                }
              }
            ]
          },
          {
            "matcher": {
              "id": "byName",
              "options": "RAM Usage"
            },
            "properties": [
              {
                "id": "custom.width",
                "value": 120
              },
              {
                "id": "thresholds",
                "value": {
                  "mode": "absolute",
                  "steps": [
                    {
                      "color": "#55a64bb0",
                      "value": null
                    },
                    {
                      "color": "#e02f44b0",
                      "value": 80
                    }
                  ]
                }
              },
              {
                "id": "custom.displayMode",
                "value": "color-background-solid"
              },
              {
                "id": "unit",
                "value": "percent"
              }
            ]
          },
          {
            "matcher": {
              "id": "byName",
              "options": "Total RAM"
            },
            "properties": [
              {
                "id": "custom.width",
                "value": 120
              },
              {
                "id": "custom.displayMode",
                "value": "color-background-solid"
              },
              {
                "id": "thresholds",
                "value": {
                  "mode": "absolute",
                  "steps": [
                    {
                      "color": "#e02f44b0",
                      "value": null
                    },
                    {
                      "color": "#55a64bb0",
                      "value": 8
                    }
                  ]
                }
              },
              {
                "id": "unit",
                "value": "decgbytes"
              }
            ]
          },
          {
            "matcher": {
              "id": "byName",
              "options": "Version"
            },
            "properties": [
              {
                "id": "custom.width"
              }
            ]
          },
          {
            "matcher": {
              "id": "byName",
              "options": "Node"
            },
            "properties": [
              {
                "id": "links",
                "value": [
                  {
                    "title": "Node Overview Dashboard",
                    "url": "/d/Dx-2iOc7k/node-overview-7-x?orgId=1&${cluster:queryparam}&${cluster_uuid:queryparam}&var-node=${__data.fields.Node}"
                  }
                ]
              }
            ]
          }
        ]
      },
      "gridPos": {
        "h": 5,
        "w": 21,
        "x": 3,
        "y": 9
      },
      "id": 2,
      "options": {
        "showHeader": true,
        "sortBy": [
          {
            "desc": true,
            "displayName": "Health Check Warnings"
          }
        ]
      },
      "pluginVersion": "8.2.5",
      "targets": [
        {
          "cacheDurationSeconds": 0,
          "datasource": "JSON API",
          "fields": [
            {
              "jsonPath": "$map($.nodes_summary[*].host, function($h) {\n    $replace(\n      $replace($h, /:\\d+$/, \"\")\n    , /https?:\\/\\//, \"\")\n})",
              "language": "jsonata",
              "name": "Node"
            },
            {
              "jsonPath": "$map($.nodes_summary[*].version, function($m) {$join($append($split($m, \"-\")[0], $replace($split($m, \"-\")[2], \"e\", \"E\", 1)), \" \")})",
              "language": "jsonata",
              "name": "Version"
            },
            {
              "jsonPath": "$.nodes_summary[*].os",
              "language": "jsonpath",
              "name": "Operating System"
            },
            {
              "jsonPath": "$map($.nodes_summary[*], function($node) {\n  $join($sort($map($node.services, function ($svc) {\n    $svc = \"cbas\" ? \"Analytics\" :\n    $svc = \"n1ql\" ? \"Query\" :\n    $svc = \"eventing\" ? \"Eventing\" :\n    $svc = \"index\" ? \"Index\" :\n    $svc = \"fts\" ? \"Search\" :\n    $svc = \"kv\" ? \"Data\" :\n    $svc = \"backup\" ? \"Backup\" : $svc\n  })), \", \")\n})",
              "language": "jsonata",
              "name": "Services"
            },
            {
              "jsonPath": "$.nodes_summary[*].cpuCount",
              "language": "jsonata",
              "name": "CPUs"
            },
            {
              "jsonPath": "$map($.nodes_summary, function ($node) {\n  $formatNumber($round($node.mem_total / 1024 / 1024 / 1024), \"####;(#0.00)\")\n})",
              "language": "jsonata",
              "name": "Total RAM"
            },
            {
              "jsonPath": "$map($.nodes_summary, function ($node) {\n  $round((1 - ($node.mem_free / $node.mem_total)) * 100, 2)\n})",
              "language": "jsonata",
              "name": "RAM Usage"
            },
            {
              "jsonPath": "$.nodes_summary[*].node_uuid",
              "language": "jsonpath",
              "name": "uuid"
            }
          ],
          "method": "GET",
          "queryParams": "",
          "refId": "A",
          "urlPath": "/clusters/$cluster_uuid"
        }
      ],
      "title": "Nodes",
      "transformations": [
        {
          "id": "labelsToFields",
          "options": {}
        },
        {
          "id": "merge",
          "options": {}
        },
        {
          "id": "organize",
          "options": {
            "excludeByName": {
              "Time": true,
              "uuid": true
            },
            "indexByName": {},
            "renameByName": {
              "Value": "Health Check Warnings",
              "hostname": "Hostname"
            }
          }
        }
      ],
      "type": "table"
    },
    {
      "datasource": "JSON API",
      "fieldConfig": {
        "defaults": {
          "color": {
            "mode": "fixed"
          },
          "mappings": [],
          "thresholds": {
            "mode": "absolute",
            "steps": [
              {
                "color": "text",
                "value": null
              }
            ]
          }
        },
        "overrides": []
      },
      "gridPos": {
        "h": 5,
        "w": 3,
        "x": 0,
        "y": 14
      },
      "id": 55,
      "options": {
        "colorMode": "value",
        "graphMode": "area",
        "justifyMode": "auto",
        "orientation": "auto",
        "reduceOptions": {
          "calcs": [
            "lastNotNull"
          ],
          "fields": "",
          "values": true
        },
        "text": {},
        "textMode": "auto"
      },
      "pluginVersion": "8.2.5",
      "targets": [
        {
          "cacheDurationSeconds": 0,
          "fields": [
            {
              "jsonPath": "$count($.buckets_summary[*])",
              "language": "jsonata",
              "name": "Number of buckets"
            }
          ],
          "method": "GET",
          "queryParams": "",
          "refId": "A",
          "urlPath": "/clusters/$cluster_uuid"
        }
      ],
      "title": "Buckets",
      "type": "stat"
    },
    {
      "datasource": "-- Mixed --",
      "description": "Couchbase recommends at least one replica, keeping Resident Ratio above 10%, and Quota used below 80%.",
      "fieldConfig": {
        "defaults": {
          "color": {
            "mode": "thresholds"
          },
          "custom": {
            "align": "center",
            "displayMode": "auto",
            "minWidth": 1
          },
          "mappings": [],
          "thresholds": {
            "mode": "absolute",
            "steps": [
              {
                "color": "text",
                "value": null
              }
            ]
          }
        },
        "overrides": [
          {
            "matcher": {
              "id": "byName",
              "options": "Quota"
            },
            "properties": [
              {
                "id": "custom.width",
                "value": 160
              },
              {
                "id": "unit",
                "value": "decgbytes"
              }
            ]
          },
          {
            "matcher": {
              "id": "byName",
              "options": "Items Stored"
            },
            "properties": [
              {
                "id": "custom.width"
              }
            ]
          },
          {
            "matcher": {
              "id": "byName",
              "options": "Quota Used"
            },
            "properties": [
              {
                "id": "custom.width",
                "value": 90
              },
              {
                "id": "unit",
                "value": "percent"
              },
              {
                "id": "custom.displayMode",
                "value": "color-background-solid"
              },
              {
                "id": "thresholds",
                "value": {
                  "mode": "absolute",
                  "steps": [
                    {
                      "color": "#55a64bb0",
                      "value": null
                    },
                    {
                      "color": "#e02f44b0",
                      "value": 80
                    }
                  ]
                }
              },
              {
                "id": "unit",
                "value": "percent"
              }
            ]
          },
          {
            "matcher": {
              "id": "byName",
              "options": "Replicas"
            },
            "properties": [
              {
                "id": "custom.width"
              }
            ]
          },
          {
            "matcher": {
              "id": "byName",
              "options": "Active Resident Ratio"
            },
            "properties": [
              {
                "id": "unit",
                "value": "percentunit"
              },
              {
                "id": "custom.width",
                "value": 160
              },
              {
                "id": "thresholds",
                "value": {
                  "mode": "absolute",
                  "steps": [
                    {
                      "color": "#e02f44b0",
                      "value": null
                    },
                    {
                      "color": "#55a64bb0",
                      "value": 0.1
                    }
                  ]
                }
              },
              {
                "id": "custom.displayMode",
                "value": "color-background-solid"
              },
              {
                "id": "mappings",
                "value": [
                  {
                    "options": {
                      "match": "null",
                      "result": {
                        "index": 0,
                        "text": "Fetching..."
                      }
                    },
                    "type": "special"
                  }
                ]
              }
            ]
          },
          {
            "matcher": {
              "id": "byName",
              "options": "# Indexes"
            },
            "properties": [
              {
                "id": "custom.width",
                "value": 80
              }
            ]
          },
          {
            "matcher": {
              "id": "byName",
              "options": "Bucket"
            },
            "properties": [
              {
                "id": "links",
                "value": [
                  {
                    "title": "Overview Dashboard",
                    "url": "/d/H8M3rE5nk/bucket-overview?${cluster:queryparam}﻿&var-bucket=${__data.fields.Bucket}"
                  }
                ]
              }
            ]
          },
          {
            "matcher": {
              "id": "byName",
              "options": "Replicas"
            },
            "properties": [
              {
                "id": "custom.width",
                "value": 70
              },
              {
                "id": "thresholds",
                "value": {
                  "mode": "absolute",
                  "steps": [
                    {
                      "color": "#ff780ab0",
                      "value": null
                    },
                    {
                      "color": "#55a64bb0",
                      "value": 1
                    }
                  ]
                }
              },
              {
                "id": "custom.displayMode",
                "value": "color-background-solid"
              }
            ]
          },
          {
            "matcher": {
              "id": "byName",
              "options": "# Indexes"
            },
            "properties": [
              {
                "id": "custom.displayMode",
                "value": "color-background-solid"
              },
              {
                "id": "thresholds",
                "value": {
                  "mode": "absolute",
                  "steps": [
                    {
                      "color": "text",
                      "value": null
                    },
                    {
                      "color": "#55a64bb3",
                      "value": 0
                    }
                  ]
                }
              },
              {
                "id": "mappings",
                "value": [
                  {
                    "options": {
                      "match": "null",
                      "result": {
                        "index": 0,
                        "text": "Fetching..."
                      }
                    },
                    "type": "special"
                  }
                ]
              }
            ]
          }
        ]
      },
      "gridPos": {
        "h": 5,
        "w": 21,
        "x": 3,
        "y": 14
      },
      "id": 48,
      "options": {
        "frameIndex": 1,
        "showHeader": true,
        "sortBy": [
          {
            "desc": true,
            "displayName": "Health Check Warnings"
          }
        ]
      },
      "pluginVersion": "8.2.5",
      "targets": [
        {
          "cacheDurationSeconds": 0,
          "datasource": "JSON API",
          "fields": [
            {
              "jsonPath": "$.buckets_summary[*].name",
              "name": "bucket"
            },
            {
              "jsonPath": "$map($.buckets_summary[*], function($b) {\n  $formatNumber($b.items, \"#,###\")\n})",
              "language": "jsonata",
              "name": "Items Stored"
            },
            {
              "jsonPath": "$map($.buckets_summary[*], function($b) {\n  $b.quota / 1024 / 1024 / 1024\n})",
              "language": "jsonata",
              "name": "Quota"
            },
            {
              "jsonPath": "$map($.buckets_summary[*], function($b) {\n  $round($b.quota_used, 2)\n})",
              "language": "jsonata",
              "name": "Quota Used",
              "type": "number"
            },
            {
              "jsonPath": "$.buckets_summary[*].num_replicas",
              "language": "jsonata",
              "name": "Replicas"
            }
          ],
          "method": "GET",
          "queryParams": "",
          "refId": "BaseData",
          "urlPath": "/clusters/$cluster_uuid"
        },
        {
          "cacheDurationSeconds": 300,
          "datasource": "Prometheus",
          "exemplar": true,
          "expr": "count by (bucket) (index_items_count{cluster=`$cluster`}) or max by (bucket) (clamp_max(kv_ops, 0))",
          "fields": [
            {
              "jsonPath": ""
            }
          ],
          "format": "table",
          "hide": false,
          "instant": true,
          "interval": "",
          "legendFormat": "",
          "method": "GET",
          "queryParams": "",
          "refId": "NumIndexes",
          "urlPath": ""
        },
        {
          "datasource": "Prometheus",
          "exemplar": true,
          "expr": "min by (bucket) (kv_vb_perc_mem_resident_ratio{cluster=`$cluster`,state=\"active\"})",
          "format": "table",
          "hide": false,
          "interval": "",
          "legendFormat": "",
          "refId": "ResidentRatio"
        }
      ],
      "title": "Dataset",
      "transformations": [
        {
          "id": "labelsToFields",
          "options": {}
        },
        {
          "id": "seriesToColumns",
          "options": {
            "byField": "bucket"
          }
        },
        {
          "id": "organize",
          "options": {
            "excludeByName": {
              "Time": true
            },
            "indexByName": {
              "Items Stored": 1,
              "Quota": 2,
              "Quota Used": 3,
              "Replicas": 5,
              "Time": 6,
              "Value #CheckWarnings": 8,
              "Value #NumIndexes": 7,
              "Value #ResidentRatio": 4,
              "bucket": 0
            },
            "renameByName": {
              "Value #CheckWarnings": "Health Check Warnings",
              "Value #NumIndexes": "# Indexes",
              "Value #ResidentRatio": "Active Resident Ratio",
              "bucket": "Bucket"
            }
          }
        }
      ],
      "type": "table"
    },
    {
      "collapsed": false,
      "datasource": null,
      "gridPos": {
        "h": 1,
        "w": 24,
        "x": 0,
        "y": 19
      },
      "id": 14,
      "panels": [],
      "title": "Health Status",
      "type": "row"
    },
    {
      "datasource": null,
      "fieldConfig": {
        "defaults": {
          "color": {
            "mode": "thresholds"
          },
          "custom": {
            "align": "center",
            "displayMode": "auto",
            "filterable": true,
            "minWidth": 1
          },
          "links": [],
          "mappings": [
            {
              "options": {
                "0": {
                  "index": 0,
                  "text": "Good"
                },
                "10": {
                  "index": 3,
                  "text": "Info"
                },
                "20": {
                  "index": 1,
                  "text": "Warn"
                },
                "30": {
                  "index": 2,
                  "text": "Alert"
                },
                "-1": {
                  "index": 4,
                  "text": "Missing"
                }
              },
              "type": "value"
            }
          ],
          "thresholds": {
            "mode": "absolute",
            "steps": [
              {
                "color": "transparent",
                "value": null
              },
              {
                "color": "transparent",
                "value": -1
              },
              {
                "color": "#37872db0",
                "value": 0
              },
              {
                "color": "#c8c8ceb0",
                "value": 10
              },
              {
                "color": "#ff9830b0",
                "value": 20
              },
              {
                "color": "#f2495cb0",
                "value": 30
              }
            ]
          }
        },
        "overrides": [
          {
            "matcher": {
              "id": "byName",
              "options": "Value"
            },
            "properties": [
              {
                "id": "custom.displayMode",
                "value": "color-background-solid"
              }
            ]
          },
          {
            "matcher": {
              "id": "byName",
              "options": "State"
            },
            "properties": [
              {
                "id": "custom.width"
              }
            ]
          },
          {
            "matcher": {
              "id": "byName",
              "options": "ID"
            },
            "properties": [
              {
                "id": "custom.width"
              },
              {
                "id": "links",
                "value": [
                  {
                    "targetBlank": true,
                    "title": "Checker Documentation",
                    "url": "/public/cmos-doc-redirect.html#/cmos/cmos/0.1/couchbase-cluster-monitor/checkers.html#${__data.fields.ID}"
                  }
                ]
              }
            ]
          },
          {
            "matcher": {
              "id": "byName",
              "options": "State"
            },
            "properties": [
              {
                "id": "links",
                "value": [
                  {
                    "targetBlank": true,
                    "title": "Checker Documentation",
                    "url": "/public/cmos-doc-redirect.html#/cmos/cmos/0.1/couchbase-cluster-monitor/checkers.html#${__data.fields.ID}"
                  }
                ]
              }
            ]
          }
        ]
      },
      "gridPos": {
        "h": 9,
        "w": 7,
        "x": 0,
        "y": 20
      },
      "id": 68,
      "options": {
        "showHeader": true,
        "sortBy": [
          {
            "desc": true,
            "displayName": "State"
          }
        ]
      },
      "pluginVersion": "8.2.5",
      "targets": [
        {
          "exemplar": true,
          "expr": "multimanager_cluster_checker_status{cluster_uuid=\"$cluster_uuid\"}",
          "instant": true,
          "interval": "",
          "legendFormat": "",
          "refId": "A"
        }
      ],
      "title": "Cluster Check Status",
      "transformations": [
        {
          "id": "labelsToFields",
          "options": {}
        },
        {
          "id": "merge",
          "options": {}
        },
        {
          "id": "organize",
          "options": {
            "excludeByName": {
              "Time": true,
              "cluster_name": true,
              "cluster_uuid": true,
              "instance": true,
              "job": true
            },
            "indexByName": {
              "Time": 0,
              "Value": 7,
              "cluster_name": 1,
              "cluster_uuid": 2,
              "id": 3,
              "instance": 5,
              "job": 6,
              "name": 4
            },
            "renameByName": {
              "Value": "State",
              "id": "ID",
              "name": "Name"
            }
          }
        }
      ],
      "type": "table"
    },
    {
      "datasource": null,
      "fieldConfig": {
        "defaults": {
          "color": {
            "mode": "thresholds"
          },
          "custom": {
            "align": "center",
            "displayMode": "auto",
            "filterable": true,
            "minWidth": 1
          },
          "links": [],
          "mappings": [
            {
              "options": {
                "0": {
                  "index": 0,
                  "text": "Good"
                },
                "10": {
                  "index": 3,
                  "text": "Info"
                },
                "20": {
                  "index": 1,
                  "text": "Warn"
                },
                "30": {
                  "index": 2,
                  "text": "Alert"
                },
                "-1": {
                  "index": 4,
                  "text": "Missing"
                }
              },
              "type": "value"
            }
          ],
          "thresholds": {
            "mode": "absolute",
            "steps": [
              {
                "color": "transparent",
                "value": null
              },
              {
                "color": "transparent",
                "value": -1
              },
              {
                "color": "#37872db0",
                "value": 0
              },
              {
                "color": "#c8c8ceb0",
                "value": 10
              },
              {
                "color": "#ff9830b0",
                "value": 20
              },
              {
                "color": "#f2495cb0",
                "value": 30
              }
            ]
          }
        },
        "overrides": [
          {
            "matcher": {
              "id": "byName",
              "options": "Value"
            },
            "properties": [
              {
                "id": "custom.displayMode",
                "value": "color-background-solid"
              }
            ]
          },
          {
            "matcher": {
              "id": "byName",
              "options": "State"
            },
            "properties": [
              {
                "id": "custom.width"
              }
            ]
          },
          {
            "matcher": {
              "id": "byName",
              "options": "ID"
            },
            "properties": [
              {
                "id": "custom.width"
              },
              {
                "id": "links",
                "value": [
                  {
                    "targetBlank": true,
                    "title": "Checker Documentation",
                    "url": "/public/cmos-doc-redirect.html#/cmos/cmos/0.1/couchbase-cluster-monitor/checkers.html#${__data.fields.ID}"
                  }
                ]
              }
            ]
          },
          {
            "matcher": {
              "id": "byName",
              "options": "Node"
            },
            "properties": [
              {
                "id": "links",
                "value": [
                  {
                    "title": "Node Overview",
                    "url": "/d/Dx-2iOc7k/node-overview-7-x?orgId=1&${cluster:queryparam}&$${cluster_uuid:queryparam}&var-node=${__data.fields.Node}"
                  }
                ]
              }
            ]
          },
          {
            "matcher": {
              "id": "byName",
              "options": "State"
            },
            "properties": [
              {
                "id": "links",
                "value": [
                  {
                    "targetBlank": true,
                    "title": "Checkers Documentation",
                    "url": "/public/cmos-doc-redirect.html#/cmos/cmos/0.1/couchbase-cluster-monitor/checkers.html#${__data.fields.ID}"
                  }
                ]
              }
            ]
          }
        ]
      },
      "gridPos": {
        "h": 9,
        "w": 8,
        "x": 7,
        "y": 20
      },
      "id": 105,
      "options": {
        "showHeader": true,
        "sortBy": [
          {
            "desc": true,
            "displayName": "State"
          }
        ]
      },
      "pluginVersion": "8.2.5",
      "targets": [
        {
          "exemplar": true,
          "expr": "multimanager_node_checker_status{cluster_uuid=\"$cluster_uuid\"}",
          "instant": true,
          "interval": "",
          "legendFormat": "",
          "refId": "A"
        }
      ],
      "title": "Node Check Status",
      "transformations": [
        {
          "id": "labelsToFields",
          "options": {}
        },
        {
          "id": "merge",
          "options": {}
        },
        {
          "id": "organize",
          "options": {
            "excludeByName": {
              "Time": true,
              "cluster_name": true,
              "cluster_uuid": true,
              "instance": true,
              "job": true,
              "node_name": false,
              "node_uuid": true
            },
            "indexByName": {
              "Time": 0,
              "Value": 8,
              "cluster_name": 1,
              "cluster_uuid": 2,
              "id": 3,
              "instance": 5,
              "job": 7,
              "name": 4,
              "node_name": 6,
              "node_uuid": 9
            },
            "renameByName": {
              "Value": "State",
              "id": "ID",
              "name": "Name",
              "node_name": "Node"
            }
          }
        }
      ],
      "type": "table"
    },
    {
      "datasource": null,
      "fieldConfig": {
        "defaults": {
          "color": {
            "mode": "thresholds"
          },
          "custom": {
            "align": "center",
            "displayMode": "auto",
            "filterable": true,
            "minWidth": 1
          },
          "links": [],
          "mappings": [
            {
              "options": {
                "0": {
                  "index": 0,
                  "text": "Good"
                },
                "10": {
                  "index": 3,
                  "text": "Info"
                },
                "20": {
                  "index": 1,
                  "text": "Warn"
                },
                "30": {
                  "index": 2,
                  "text": "Alert"
                },
                "-1": {
                  "index": 4,
                  "text": "Missing"
                }
              },
              "type": "value"
            }
          ],
          "thresholds": {
            "mode": "absolute",
            "steps": [
              {
                "color": "transparent",
                "value": null
              },
              {
                "color": "transparent",
                "value": -1
              },
              {
                "color": "#37872db0",
                "value": 0
              },
              {
                "color": "#c8c8ceb0",
                "value": 10
              },
              {
                "color": "#ff9830b0",
                "value": 20
              },
              {
                "color": "#f2495cb0",
                "value": 30
              }
            ]
          }
        },
        "overrides": [
          {
            "matcher": {
              "id": "byName",
              "options": "Value"
            },
            "properties": [
              {
                "id": "custom.displayMode",
                "value": "color-background-solid"
              }
            ]
          },
          {
            "matcher": {
              "id": "byName",
              "options": "ID"
            },
            "properties": [
              {
                "id": "custom.width"
              },
              {
                "id": "links",
                "value": [
                  {
                    "targetBlank": true,
                    "title": "Checker Documentation",
                    "url": "/public/cmos-doc-redirect.html#/cmos/cmos/0.1/couchbase-cluster-monitor/checkers.html#${__data.fields.ID}"
                  }
                ]
              }
            ]
          },
          {
            "matcher": {
              "id": "byName",
              "options": "Bucket"
            },
            "properties": [
              {
                "id": "links",
                "value": [
                  {
                    "targetBlank": true,
                    "title": "Bucket Overview",
                    "url": "/d/H8M3rE5nk/bucket-overview?${cluster:queryparam}﻿&var-bucket=${__data.fields.Bucket}"
                  }
                ]
              }
            ]
          },
          {
            "matcher": {
              "id": "byName",
              "options": "State"
            },
            "properties": [
              {
                "id": "links",
                "value": [
                  {
                    "targetBlank": true,
                    "title": "Checker Documentation",
                    "url": "/public/cmos-doc-redirect.html#/cmos/cmos/0.1/couchbase-cluster-monitor/checkers.html#${__data.fields.ID}"
                  }
                ]
              }
            ]
          }
        ]
      },
      "gridPos": {
        "h": 9,
        "w": 9,
        "x": 15,
        "y": 20
      },
      "id": 106,
      "options": {
        "showHeader": true,
        "sortBy": [
          {
            "desc": true,
            "displayName": "State"
          }
        ]
      },
      "pluginVersion": "8.2.5",
      "targets": [
        {
          "exemplar": true,
          "expr": "multimanager_bucket_checker_status{cluster_uuid=\"$cluster_uuid\"}",
          "instant": true,
          "interval": "",
          "legendFormat": "",
          "refId": "A"
        }
      ],
      "title": "Bucket Check Status",
      "transformations": [
        {
          "id": "labelsToFields",
          "options": {}
        },
        {
          "id": "merge",
          "options": {}
        },
        {
          "id": "organize",
          "options": {
            "excludeByName": {
              "Time": true,
              "bucket": false,
              "cluster_name": true,
              "cluster_uuid": true,
              "instance": true,
              "job": true,
              "node_name": true,
              "node_uuid": true
            },
            "indexByName": {
              "Time": 0,
              "Value": 8,
              "bucket": 5,
              "cluster_name": 1,
              "cluster_uuid": 2,
              "id": 3,
              "instance": 6,
              "job": 7,
              "name": 4
            },
            "renameByName": {
              "Value": "State",
              "bucket": "Bucket",
              "id": "ID",
              "name": "Name"
            }
          }
        }
      ],
      "type": "table"
    },
    {
      "collapsed": false,
      "datasource": null,
      "gridPos": {
        "h": 1,
        "w": 24,
        "x": 0,
        "y": 29
      },
      "id": 110,
      "panels": [],
      "title": "System resources",
      "type": "row"
    },
    {
      "datasource": null,
      "fieldConfig": {
        "defaults": {
          "color": {
            "mode": "thresholds"
          },
          "custom": {
            "axisLabel": "",
            "axisPlacement": "auto",
            "barAlignment": 0,
            "drawStyle": "line",
            "fillOpacity": 40,
            "gradientMode": "opacity",
            "hideFrom": {
              "legend": false,
              "tooltip": false,
              "viz": false
            },
            "lineInterpolation": "linear",
            "lineStyle": {
              "fill": "solid"
            },
            "lineWidth": 1,
            "pointSize": 5,
            "scaleDistribution": {
              "type": "linear"
            },
            "showPoints": "auto",
            "spanNulls": false,
            "stacking": {
              "group": "A",
              "mode": "none"
            },
            "thresholdsStyle": {
              "mode": "line"
            }
          },
          "mappings": [],
          "thresholds": {
            "mode": "absolute",
            "steps": [
              {
                "color": "#73bf69b0",
                "value": null
              },
              {
                "color": "#ebb838b0",
                "value": 70
              },
              {
                "color": "#f2495cb0",
                "value": 80
              }
            ]
          },
          "unit": "percent"
        },
        "overrides": []
      },
      "gridPos": {
        "h": 10,
        "w": 12,
        "x": 0,
        "y": 30
      },
      "id": 114,
      "options": {
        "legend": {
          "calcs": [],
          "displayMode": "list",
          "placement": "bottom"
        },
        "tooltip": {
          "mode": "single"
        }
      },
      "targets": [
        {
          "exemplar": true,
          "expr": "sys_cpu_utilization_rate{cluster=${cluster:doublequote}}",
          "interval": "",
          "legendFormat": "{{instance}}",
          "refId": "A"
        }
      ],
      "title": "CPU Utilization",
      "type": "timeseries"
    },
    {
      "datasource": null,
      "fieldConfig": {
        "defaults": {
          "color": {
            "mode": "palette-classic"
          },
          "custom": {
            "axisLabel": "",
            "axisPlacement": "auto",
            "barAlignment": 0,
            "drawStyle": "line",
            "fillOpacity": 40,
            "gradientMode": "opacity",
            "hideFrom": {
              "legend": false,
              "tooltip": false,
              "viz": false
            },
            "lineInterpolation": "linear",
            "lineWidth": 1,
            "pointSize": 5,
            "scaleDistribution": {
              "type": "linear"
            },
            "showPoints": "auto",
            "spanNulls": false,
            "stacking": {
              "group": "A",
              "mode": "none"
            },
            "thresholdsStyle": {
              "mode": "off"
            }
          },
          "mappings": [],
          "thresholds": {
            "mode": "absolute",
            "steps": [
              {
                "color": "#73bf69b0",
                "value": null
              },
              {
                "color": "#ebb838b0",
                "value": 0.7
              },
              {
                "color": "#f2495cb0",
                "value": 0.8
              }
            ]
          },
          "unit": "percentunit"
        },
        "overrides": []
      },
      "gridPos": {
        "h": 10,
        "w": 12,
        "x": 12,
        "y": 30
      },
      "id": 116,
      "options": {
        "legend": {
          "calcs": [],
          "displayMode": "list",
          "placement": "bottom"
        },
        "tooltip": {
          "mode": "single"
        }
      },
      "pluginVersion": "8.2.5",
      "targets": [
        {
          "exemplar": true,
          "expr": "sys_mem_free{cluster=${cluster:doublequote}} / \nsys_mem_total{cluster=${cluster:doublequote}}",
          "format": "time_series",
          "instant": false,
          "interval": "",
          "legendFormat": "{{instance}}",
          "refId": "A"
        }
      ],
      "title": "Memory Usage",
      "type": "timeseries"
    },
    {
      "collapsed": false,
      "datasource": null,
      "gridPos": {
        "h": 1,
        "w": 24,
        "x": 0,
        "y": 40
      },
      "id": 16,
      "panels": [],
      "title": "KPIs - Data Service",
      "type": "row"
    },
    {
      "datasource": null,
      "fieldConfig": {
        "defaults": {
          "color": {
            "mode": "palette-classic"
          },
          "custom": {
            "axisLabel": "",
            "axisPlacement": "auto",
            "barAlignment": 0,
            "drawStyle": "line",
            "fillOpacity": 40,
            "gradientMode": "opacity",
            "hideFrom": {
              "legend": false,
              "tooltip": false,
              "viz": false
            },
            "lineInterpolation": "linear",
            "lineWidth": 1,
            "pointSize": 5,
            "scaleDistribution": {
              "type": "linear"
            },
            "showPoints": "auto",
            "spanNulls": false,
            "stacking": {
              "group": "A",
              "mode": "none"
            },
            "thresholdsStyle": {
              "mode": "off"
            }
          },
          "mappings": [],
          "thresholds": {
            "mode": "percentage",
            "steps": [
              {
                "color": "#3275d9b0",
                "value": null
              }
            ]
          },
          "unit": "ops"
        },
        "overrides": []
      },
      "gridPos": {
        "h": 10,
        "w": 12,
        "x": 0,
        "y": 41
      },
      "id": 28,
      "options": {
        "legend": {
          "calcs": [],
          "displayMode": "list",
          "placement": "bottom"
        },
        "tooltip": {
          "mode": "single"
        }
      },
      "targets": [
        {
          "exemplar": true,
          "expr": "sum by (instance) (rate(kv_ops{cluster=\"$cluster\",op=\"get\"}[$__rate_interval]))",
          "interval": "",
          "legendFormat": "{{ instance}}",
          "refId": "A"
        }
      ],
      "title": "Reads per second",
      "type": "timeseries"
    },
    {
      "datasource": null,
      "fieldConfig": {
        "defaults": {
          "color": {
            "mode": "palette-classic",
            "seriesBy": "max"
          },
          "custom": {
            "axisLabel": "",
            "axisPlacement": "auto",
            "barAlignment": 0,
            "drawStyle": "line",
            "fillOpacity": 40,
            "gradientMode": "opacity",
            "hideFrom": {
              "legend": false,
              "tooltip": false,
              "viz": false
            },
            "lineInterpolation": "linear",
            "lineWidth": 1,
            "pointSize": 5,
            "scaleDistribution": {
              "type": "linear"
            },
            "showPoints": "auto",
            "spanNulls": false,
            "stacking": {
              "group": "A",
              "mode": "none"
            },
            "thresholdsStyle": {
              "mode": "off"
            }
          },
          "mappings": [],
          "thresholds": {
            "mode": "absolute",
            "steps": [
              {
                "color": "text",
                "value": null
              }
            ]
          },
          "unit": "s"
        },
        "overrides": []
      },
      "gridPos": {
        "h": 10,
        "w": 12,
        "x": 12,
        "y": 41
      },
      "id": 102,
      "options": {
        "legend": {
          "calcs": [],
          "displayMode": "list",
          "placement": "bottom"
        },
        "tooltip": {
          "mode": "single"
        }
      },
      "targets": [
        {
          "exemplar": true,
          "expr": "max(histogram_quantile(0.50, sum by(le,bucket) (rate(kv_cmd_duration_seconds_bucket{cluster=`$cluster`,opcode=\"GET\"}[5m]))))",
          "hide": false,
          "interval": "",
          "legendFormat": "50th percentile (avg)",
          "refId": "C"
        },
        {
          "exemplar": true,
          "expr": "max(histogram_quantile(0.99, sum by(le,bucket) (rate(kv_cmd_duration_seconds_bucket{cluster=`$cluster`,opcode=\"GET\"}[5m]))))",
          "instant": false,
          "interval": "",
          "legendFormat": "99th percentile",
          "refId": "A"
        },
        {
          "exemplar": true,
          "expr": "max(histogram_quantile(0.999, sum by(le,bucket) (rate(kv_cmd_duration_seconds_bucket{cluster=`$cluster`,opcode=\"GET\"}[5m]))))",
          "hide": false,
          "interval": "",
          "legendFormat": "99.9th percentile",
          "refId": "B"
        }
      ],
      "title": "Read latency",
      "type": "timeseries"
    },
    {
      "datasource": null,
      "fieldConfig": {
        "defaults": {
          "color": {
            "mode": "palette-classic"
          },
          "custom": {
            "axisLabel": "",
            "axisPlacement": "auto",
            "barAlignment": 0,
            "drawStyle": "line",
            "fillOpacity": 40,
            "gradientMode": "opacity",
            "hideFrom": {
              "legend": false,
              "tooltip": false,
              "viz": false
            },
            "lineInterpolation": "linear",
            "lineWidth": 1,
            "pointSize": 5,
            "scaleDistribution": {
              "type": "linear"
            },
            "showPoints": "auto",
            "spanNulls": false,
            "stacking": {
              "group": "A",
              "mode": "none"
            },
            "thresholdsStyle": {
              "mode": "off"
            }
          },
          "mappings": [],
          "thresholds": {
            "mode": "percentage",
            "steps": [
              {
                "color": "#3275d9b0",
                "value": null
              }
            ]
          },
          "unit": "ops"
        },
        "overrides": []
      },
      "gridPos": {
        "h": 10,
        "w": 12,
        "x": 0,
        "y": 51
      },
      "id": 107,
      "options": {
        "legend": {
          "calcs": [],
          "displayMode": "list",
          "placement": "bottom"
        },
        "tooltip": {
          "mode": "single"
        }
      },
      "targets": [
        {
          "exemplar": true,
          "expr": "sum by (instance) (rate(kv_ops{cluster=\"$cluster\",op=\"set\"}[$__rate_interval]))",
          "interval": "",
          "legendFormat": "{{ instance}}",
          "refId": "A"
        }
      ],
      "title": "Writes per second",
      "type": "timeseries"
    },
    {
      "datasource": null,
      "fieldConfig": {
        "defaults": {
          "color": {
            "mode": "palette-classic",
            "seriesBy": "last"
          },
          "custom": {
            "axisLabel": "",
            "axisPlacement": "auto",
            "barAlignment": 0,
            "drawStyle": "line",
            "fillOpacity": 40,
            "gradientMode": "opacity",
            "hideFrom": {
              "legend": false,
              "tooltip": false,
              "viz": false
            },
            "lineInterpolation": "linear",
            "lineWidth": 1,
            "pointSize": 5,
            "scaleDistribution": {
              "type": "linear"
            },
            "showPoints": "auto",
            "spanNulls": false,
            "stacking": {
              "group": "A",
              "mode": "none"
            },
            "thresholdsStyle": {
              "mode": "off"
            }
          },
          "mappings": [],
          "thresholds": {
            "mode": "absolute",
            "steps": [
              {
                "color": "text",
                "value": null
              }
            ]
          },
          "unit": "s"
        },
        "overrides": []
      },
      "gridPos": {
        "h": 10,
        "w": 12,
        "x": 12,
        "y": 51
      },
      "id": 108,
      "options": {
        "legend": {
          "calcs": [],
          "displayMode": "list",
          "placement": "bottom"
        },
        "tooltip": {
          "mode": "single"
        }
      },
      "targets": [
        {
          "exemplar": true,
          "expr": "max(histogram_quantile(0.50, sum by(le,bucket) (rate(kv_cmd_duration_seconds_bucket{cluster=`$cluster`,opcode=\"SET\"}[5m]))))",
          "hide": false,
          "interval": "",
          "legendFormat": "50th percentile (avg)",
          "refId": "C"
        },
        {
          "exemplar": true,
          "expr": "max(histogram_quantile(0.99, sum by(le,bucket) (rate(kv_cmd_duration_seconds_bucket{cluster=`$cluster`,opcode=\"SET\"}[5m]))))",
          "instant": false,
          "interval": "",
          "legendFormat": "99th percentile",
          "refId": "A"
        },
        {
          "exemplar": true,
          "expr": "max(histogram_quantile(0.999, sum by(le,bucket) (rate(kv_cmd_duration_seconds_bucket{cluster=`$cluster`,opcode=\"SET\"}[5m]))))",
          "hide": false,
          "interval": "",
          "legendFormat": "99.9th percentile",
          "refId": "B"
        }
      ],
      "title": "Write Latency",
      "type": "timeseries"
    },
    {
      "collapsed": false,
      "datasource": null,
      "gridPos": {
        "h": 1,
        "w": 24,
        "x": 0,
        "y": 61
      },
      "id": 41,
      "panels": [],
      "title": "KPIs - Query Service",
      "type": "row"
    },
    {
      "datasource": null,
      "fieldConfig": {
        "defaults": {
          "color": {
            "mode": "palette-classic",
            "seriesBy": "last"
          },
          "custom": {
            "axisLabel": "",
            "axisPlacement": "auto",
            "barAlignment": 0,
            "drawStyle": "line",
            "fillOpacity": 40,
            "gradientMode": "opacity",
            "hideFrom": {
              "legend": false,
              "tooltip": false,
              "viz": false
            },
            "lineInterpolation": "linear",
            "lineStyle": {
              "fill": "solid"
            },
            "lineWidth": 1,
            "pointSize": 5,
            "scaleDistribution": {
              "type": "linear"
            },
            "showPoints": "auto",
            "spanNulls": false,
            "stacking": {
              "group": "A",
              "mode": "none"
            },
            "thresholdsStyle": {
              "mode": "off"
            }
          },
          "mappings": [],
          "thresholds": {
            "mode": "absolute",
            "steps": [
              {
                "color": "text",
                "value": null
              }
            ]
          },
          "unit": "ops"
        },
        "overrides": []
      },
      "gridPos": {
        "h": 10,
        "w": 12,
        "x": 0,
        "y": 62
      },
      "id": 20,
      "options": {
        "legend": {
          "calcs": [],
          "displayMode": "list",
          "placement": "bottom"
        },
        "tooltip": {
          "mode": "single"
        }
      },
      "targets": [
        {
          "exemplar": true,
          "expr": "sum by (instance) (rate(n1ql_requests{cluster=\"$cluster\"}[$__rate_interval]))",
          "interval": "",
          "legendFormat": "{{instance}}",
          "refId": "A"
        }
      ],
      "title": "Queries Per Second",
      "type": "timeseries"
    },
    {
      "datasource": null,
      "fieldConfig": {
        "defaults": {
          "color": {
            "mode": "palette-classic",
            "seriesBy": "last"
          },
          "custom": {
            "axisLabel": "",
            "axisPlacement": "auto",
            "barAlignment": 0,
            "drawStyle": "line",
            "fillOpacity": 40,
            "gradientMode": "opacity",
            "hideFrom": {
              "legend": false,
              "tooltip": false,
              "viz": false
            },
            "lineInterpolation": "linear",
            "lineWidth": 1,
            "pointSize": 5,
            "scaleDistribution": {
              "type": "linear"
            },
            "showPoints": "auto",
            "spanNulls": false,
            "stacking": {
              "group": "A",
              "mode": "none"
            },
            "thresholdsStyle": {
              "mode": "off"
            }
          },
          "mappings": [],
          "thresholds": {
            "mode": "absolute",
            "steps": [
              {
                "color": "text",
                "value": null
              }
            ]
          },
          "unit": "ms"
        },
        "overrides": []
      },
      "gridPos": {
        "h": 10,
        "w": 12,
        "x": 12,
        "y": 62
      },
      "id": 24,
      "options": {
        "legend": {
          "calcs": [],
          "displayMode": "list",
          "placement": "bottom"
        },
        "tooltip": {
          "mode": "single"
        }
      },
      "pluginVersion": "8.2.3",
      "targets": [
        {
          "exemplar": true,
          "expr": "increase(n1ql_request_time[$__rate_interval]) / increase(n1ql_requests[$__rate_interval]) / 1000000\n",
          "instant": false,
          "interval": "",
          "legendFormat": "{{instance}}",
          "refId": "A"
        }
      ],
      "title": "Average Query Execution Time",
      "type": "timeseries"
    }
  ],
  "refresh": false,
  "schemaVersion": 32,
  "style": "dark",
  "tags": [
    "couchbase",
    "couchbase-7",
    "couchbase-cluster"
  ],
  "templating": {
    "list": [
      {
        "allValue": null,
        "current": {
          "selected": false,
          "text": "Cluster 0",
          "value": "Cluster 0"
        },
        "datasource": null,
        "definition": "label_values(multimanager_cluster_checker_status,cluster_name)",
        "description": null,
        "error": null,
        "hide": 0,
        "includeAll": false,
        "label": "Cluster",
        "multi": false,
        "name": "cluster",
        "options": [],
        "query": {
          "query": "label_values(multimanager_cluster_checker_status,cluster_name)",
          "refId": "StandardVariableQuery"
        },
        "refresh": 1,
        "regex": "",
        "skipUrlSync": false,
        "sort": 0,
        "type": "query"
      },
      {
        "allValue": null,
        "current": {
          "selected": false,
          "text": "1a528e14cf83548956ab971a279eb3b8",
          "value": "1a528e14cf83548956ab971a279eb3b8"
        },
        "datasource": null,
        "definition": "multimanager_cluster_checker_status{cluster_name=\"$cluster\"}",
        "description": null,
        "error": null,
        "hide": 2,
        "includeAll": false,
        "label": null,
        "multi": false,
        "name": "cluster_uuid",
        "options": [],
        "query": {
          "query": "multimanager_cluster_checker_status{cluster_name=\"$cluster\"}",
          "refId": "StandardVariableQuery"
        },
        "refresh": 1,
        "regex": "/[{,]cluster_uuid=\"(.+?)\"[,}]/",
        "skipUrlSync": false,
        "sort": 0,
        "type": "query"
      },
      {
        "allValue": null,
        "current": {
          "selected": false,
          "text": "node2.local",
          "value": "node2.local"
        },
        "datasource": null,
        "definition": "query_result(multimanager_node_checker_status{cluster_name=${cluster:doublequote}})",
        "description": null,
        "error": null,
        "hide": 2,
        "includeAll": false,
        "label": null,
        "multi": false,
        "name": "node",
        "options": [],
        "query": {
          "query": "query_result(multimanager_node_checker_status{cluster_name=${cluster:doublequote}})",
          "refId": "StandardVariableQuery"
        },
        "refresh": 1,
        "regex": "/[{,]node_name=\"(.+?)(?::[0-9]*)?\"[,}]/",
        "skipUrlSync": false,
        "sort": 0,
        "type": "query"
      }
    ]
  },
  "time": {
    "from": "now-3h",
    "to": "now"
  },
  "timepicker": {
    "refresh_intervals": [
      "5s",
      "15s",
      "30s",
      "1m",
      "5m",
      "15m",
      "30m",
      "1h",
      "2h",
      "1d"
    ]
  },
  "timezone": "",
  "title": "Single Cluster Overview",
  "uid": "UEZRQMc7z",
  "version": 2
}